sector/__init__.py
sector/auto_param_search.py
sector/comparator.py
sector/extractor.py
sector/sector_main.py
sector/data/__init__.py
sector/data/properties.json
sector/helpers/__init__.py
sector/helpers/external_metrics.py
sector/helpers/sector_helper.py
sector/utils/__init__.py
sector/utils/load_properties.py
sector/utils/logging_config.py
tests/__init__.py
tests/test_comparator.py
tests/test_extractor.py
tests/test_sector.py
tests/test_sector_transcript.py
sector-0.1.3.dist-info/LICENSE
sector-0.1.3.dist-info/METADATA
sector-0.1.3.dist-info/WHEEL
sector-0.1.3.dist-info/top_level.txt
sector-0.1.3.dist-info/RECORD
