Metadata-Version: 2.1
Name: sector
Version: 0.1.3
Summary: A Python library for semantic extraction and comparison
Home-page: https://github.com/srivatsan88/sector/
Author: Srivatsan Srinivasan
Author-email: secret@secret.com
Classifier: Programming Language :: Python :: 3
Classifier: License :: OSI Approved :: MIT License
Classifier: Operating System :: OS Independent
Requires-Python: >=3.9
License-File: LICENSE
Requires-Dist: urllib3>=1.26.19
Requires-Dist: spacy==3.8.2
Requires-Dist: nltk==3.9.1
Requires-Dist: scikit-learn==1.5.2
Requires-Dist: fuzzywuzzy==0.18.0
Requires-Dist: python-Levenshtein==0.26.0
Requires-Dist: rouge-score==0.1.2
Requires-Dist: pytest==8.3.3
Requires-Dist: streamlit==1.39.0
Requires-Dist: watchdog==5.0.3
Requires-Dist: flask==3.0.3
Requires-Dist: xlsxwriter==3.2.0
Requires-Dist: streamlit-aggrid==1.0.5
Requires-Dist: openpyxl==3.1.5
Provides-Extra: testing
Requires-Dist: pytest; extra == "testing"
Requires-Dist: pytest-cov; extra == "testing"
